jarvis_ui/__init__.py
jarvis_ui/main.py
jarvis_ui/test_listener.py
jarvis_ui/executables/api_handler.py
jarvis_ui/executables/audio_driver.py
jarvis_ui/executables/display.py
jarvis_ui/executables/helper.py
jarvis_ui/executables/listener.py
jarvis_ui/executables/speaker.py
jarvis_ui/executables/starter.py
jarvis_ui/indicators/acknowledgement.wav
jarvis_ui/indicators/connection_restart_mac.wav
jarvis_ui/indicators/connection_restart_ss.wav
jarvis_ui/indicators/connection_restart_win.wav
jarvis_ui/indicators/failed_mac.wav
jarvis_ui/indicators/failed_ss.wav
jarvis_ui/indicators/failed_win.wav
jarvis_ui/indicators/restart_mac.wav
jarvis_ui/indicators/restart_ss.wav
jarvis_ui/indicators/restart_win.wav
jarvis_ui/indicators/shutdown_mac.wav
jarvis_ui/indicators/shutdown_ss.wav
jarvis_ui/indicators/shutdown_win.wav
jarvis_ui/lib/install.sh
jarvis_ui/lib/requirements.txt
jarvis_ui/lib/squire/detector.sh
jarvis_ui/modules/config.py
jarvis_ui/modules/exceptions.py
jarvis_ui/modules/logger.py
jarvis_ui/modules/models.py
jarvis_ui/modules/peripherals.py
jarvis_ui/modules/timer.py
jarvis_ui-2.3.1.data/scripts/detector.sh
jarvis_ui-2.3.1.data/scripts/install.sh
jarvis_ui-2.3.1.dist-info/LICENSE
jarvis_ui-2.3.1.dist-info/METADATA
jarvis_ui-2.3.1.dist-info/WHEEL
jarvis_ui-2.3.1.dist-info/top_level.txt
jarvis_ui-2.3.1.dist-info/RECORD
