Metadata-Version: 2.1
Name: jarvis-ui
Version: 2.3.1
Summary: Jarvis UI to perform voice commands via API calls
Author-email: Vignesh Rao <svignesh1793@gmail.com>
License: MIT License
Project-URL: Homepage, https://github.com/thevickypedia/Jarvis_UI
Project-URL: Docs, https://thevickypedia.github.io/Jarvis_UI
Project-URL: Source, https://github.com/thevickypedia/Jarvis_UI
Project-URL: Bug Tracker, https://github.com/thevickypedia/Jarvis_UI/issues
Project-URL: Release Notes, https://github.com/thevickypedia/Jarvis_UI/blob/main/release_notes.rst
Keywords: python,natural-language-processing,text-to-speech,speech-recognition,jarvis,hotword-detection,virtual-assistant,multiprocessing,threadpool
Classifier: Development Status :: 5 - Production/Stable
Classifier: Intended Audience :: Information Technology
Classifier: Operating System :: MacOS :: MacOS X
Classifier: Operating System :: Microsoft :: Windows :: Windows 10
Classifier: Operating System :: POSIX :: Linux
Classifier: License :: OSI Approved :: MIT License
Classifier: Programming Language :: Python :: 3.8
Classifier: Programming Language :: Python :: 3.9
Classifier: Programming Language :: Python :: 3.10
Classifier: Programming Language :: Python :: 3.11
Classifier: Topic :: Multimedia :: Sound/Audio :: Speech
Classifier: Topic :: Scientific/Engineering :: Human Machine Interfaces
Classifier: Topic :: Scientific/Engineering :: Artificial Intelligence
Classifier: Topic :: Home Automation
Classifier: Topic :: Scientific/Engineering :: Image Recognition
Classifier: Topic :: System :: Hardware :: Universal Serial Bus (USB) :: Wireless Controller
Classifier: Topic :: Multimedia :: Sound/Audio :: Conversion
Classifier: Topic :: Software Development :: Libraries :: Python Modules
Classifier: Topic :: System :: Hardware :: Hardware Drivers
Classifier: Topic :: System :: Hardware :: Symmetric Multi-processing
Classifier: Topic :: System :: Hardware :: Universal Serial Bus (USB) :: Human Interface Device (HID)
Classifier: Framework :: FastAPI
Classifier: Framework :: Flake8
Classifier: Framework :: AsyncIO
Classifier: Framework :: Sphinx
Classifier: Framework :: aiohttp
Classifier: Natural Language :: English
Requires-Python: <3.12,>=3.10
License-File: LICENSE
Requires-Dist: packaging ==23.2
Requires-Dist: py3-tts
Requires-Dist: PyAudio ==0.2.14
Requires-Dist: pydantic[email] ==2.4.*
Requires-Dist: pydantic-settings ==2.0.*
Requires-Dist: pynotification
Requires-Dist: PyYAML
Requires-Dist: requests
Requires-Dist: SpeechRecognition ==3.10.0
Provides-Extra: dev
Requires-Dist: pytest ; extra == 'dev'
Requires-Dist: pre-commit ; extra == 'dev'
